{
  "version": "7",
  "dialect": "sqlite",
  "entries": [
    {
      "idx": 0,
      "version": "6",
      "when": 1772324056258,
      "tag": "0000_noisy_warbound",
      "breakpoints": true
    },
    {
      "idx": 1,
      "version": "6",
      "when": 1772325453237,
      "tag": "0001_previous_thunderbird",
      "breakpoints": true
    },
    {
      "idx": 2,
      "version": "6",
      "when": 1772327434885,
      "tag": "0002_wooden_cable",
      "breakpoints": true
    },
    {
      "idx": 3,
      "version": "6",
      "when": 1772414978288,
      "tag": "0003_mighty_kid_colt",
      "breakpoints": true
    },
    {
      "idx": 4,
      "version": "6",
      "when": 1772434299626,
      "tag": "0004_useful_wrecking_crew",
      "breakpoints": true
    }
  ]
}